MANIFEST.in
README.rst
setup.py
adi/__init__.py
adi.trash.egg-info/PKG-INFO
adi.trash.egg-info/SOURCES.txt
adi.trash.egg-info/dependency_links.txt
adi.trash.egg-info/entry_points.txt
adi.trash.egg-info/namespace_packages.txt
adi.trash.egg-info/not-zip-safe
adi.trash.egg-info/requires.txt
adi.trash.egg-info/top_level.txt
adi/trash/__init__.py
adi/trash/configure.zcml
adi/trash/interfaces.py
adi/trash/browser/__init__.py
adi/trash/browser/browser.py
adi/trash/browser/configure.zcml
adi/trash/profiles/default/actions.xml
adi/trash/profiles/default/browserlayer.xml
adi/trash/profiles/default/metadata.xml
docs/CHANGES.rst
docs/LICENSE.GPL
docs/LICENSE.txt