Metadata-Version: 1.1
Name: adi.trash
Version: 0.6
Summary: Plone addon, changing deletion-behaviour: Moves items into a trash-folder, instead of deleting them.
Home-page: https://github.com/ida/adi.trash
Author: Ida Ebkes
Author-email: contact@ida-ebkes.eu
License: GPL
Platform: UNKNOWN
Classifier: Framework :: Plone
Classifier: Framework :: Plone :: 4.3
Classifier: Programming Language :: Python
